django_sti/__init__.py
django_sti-0.0.1.dist-info/METADATA
django_sti-0.0.1.dist-info/WHEEL
django_sti-0.0.1.dist-info/top_level.txt
django_sti-0.0.1.dist-info/RECORD
