Metadata-Version: 2.4
Name: django-sti
Version: 0.0.1
Summary: Django Single Table Inheritance
Author-email: Taemin Kim <flatcoke89@gmail.com>
Classifier: Framework :: Django
Classifier: Programming Language :: Python :: 3
Classifier: License :: OSI Approved :: MIT License
Requires-Python: >=3.8
